args.py
containers.py
tricorecli.py
utils.py
tricore_cli-1.8.dist-info/LICENSE
tricore_cli-1.8.dist-info/METADATA
tricore_cli-1.8.dist-info/WHEEL
tricore_cli-1.8.dist-info/entry_points.txt
tricore_cli-1.8.dist-info/top_level.txt
tricore_cli-1.8.dist-info/RECORD
