Metadata-Version: 2.2
Name: tricore-cli
Version: 1.8
Summary: A utility script for interacting with containerized TriCore development environment
Author: Francesco Mecatti
Project-URL: Homepage, https://github.com/mc-cat-tty/tricore-dev-env
Project-URL: Issues, https://github.com/mc-cat-tty/tricore-dev-env/issues
Requires-Python: >=3.10
License-File: LICENSE
Requires-Dist: docker>=7.0.0
Requires-Dist: rich>=13.7
